resk_llm/RESK.py
resk_llm/__init__.py
resk_llm/version.py
resk_llm-2.0.11.dist-info/licenses/LICENSE.txt
resk_llm-2.0.11.dist-info/METADATA
resk_llm-2.0.11.dist-info/WHEEL
resk_llm-2.0.11.dist-info/top_level.txt
resk_llm-2.0.11.dist-info/RECORD
