Metadata-Version: 2.4
Name: resk-llm
Version: 2.0.11
Summary: Resk-LLM is a robust Python library designed to enhance security and manage context when interacting with LLM APIs. It provides a protective layer for API calls, safeguarding against common vulnerabilities and ensuring optimal performance.
Home-page: https://github.com/Resk-Security/Resk-LLM
Author: Resk
Author-email: Resk <contact@resk.fr>
License:                                  Apache License
Project-URL: Homepage, https://github.com/Resk-Security/Resk-LLM
Classifier: Programming Language :: Python :: 3
Classifier: License :: OSI Approved :: MIT License
Classifier: Operating System :: OS Independent
Requires-Python: >=3.8
License-File: LICENSE.txt
Requires-Dist: openai>=1.41.0
Requires-Dist: transformers>=4.44.2
Requires-Dist: flask>=2.0.0
Requires-Dist: fastapi>=0.110.0
Requires-Dist: uvicorn>=0.28.0
Requires-Dist: starlette>=0.36.0
Requires-Dist: anthropic>=0.22.0
Requires-Dist: cohere>=4.46.0
Requires-Dist: langchain>=0.1.0
Requires-Dist: langchain-core>=0.1.0
Requires-Dist: langchain-community>=0.1.0
Requires-Dist: langchain-openai>=0.1.0
Requires-Dist: numpy>=1.20.0
Requires-Dist: pillow>=9.0.0
Requires-Dist: pydantic>=2.0.0
Requires-Dist: requests>=2.25.0
Requires-Dist: rich>=10.0.0
Requires-Dist: typing-extensions>=4.0.0
Requires-Dist: urllib3>=1.26.0
Requires-Dist: httpx>=0.27.0
Requires-Dist: pytest>=7.4.3
Requires-Dist: pytest-asyncio>=0.23.5
Requires-Dist: tldextract>=3.4.4
Requires-Dist: mypy
Requires-Dist: PyJWT
Provides-Extra: dev
Requires-Dist: flake8>=6.0.0; extra == "dev"
Requires-Dist: mypy>=1.0.0; extra == "dev"
Requires-Dist: pytest>=7.4.3; extra == "dev"
Requires-Dist: pytest-asyncio>=0.23.5; extra == "dev"
Requires-Dist: build>=0.10.0; extra == "dev"
Requires-Dist: twine>=4.0.0; extra == "dev"
Provides-Extra: all
Requires-Dist: tiktoken>=0.5.0; extra == "all"
Requires-Dist: scikit-learn>=1.2.0; extra == "all"
Requires-Dist: faiss-cpu>=1.7.4; extra == "all"
Requires-Dist: pinecone-client>=2.2.1; extra == "all"
Requires-Dist: pymilvus>=2.3.0; extra == "all"
Requires-Dist: qdrant-client>=1.7.0; extra == "all"
Requires-Dist: weaviate-client>=3.25.0; extra == "all"
Requires-Dist: chromadb>=0.4.22; extra == "all"
Requires-Dist: tldextract>=3.4.4; extra == "all"
Requires-Dist: ipaddress>=1.0.23; extra == "all"
Provides-Extra: vector
Requires-Dist: faiss-cpu>=1.7.4; extra == "vector"
Requires-Dist: scikit-learn>=1.2.0; extra == "vector"
Provides-Extra: vector-all
Requires-Dist: faiss-cpu>=1.7.4; extra == "vector-all"
Requires-Dist: pinecone-client>=2.2.1; extra == "vector-all"
Requires-Dist: pymilvus>=2.3.0; extra == "vector-all"
Requires-Dist: qdrant-client>=1.7.0; extra == "vector-all"
Requires-Dist: weaviate-client>=3.25.0; extra == "vector-all"
Requires-Dist: chromadb>=0.4.22; extra == "vector-all"
Provides-Extra: url-security
Requires-Dist: tldextract>=3.4.4; extra == "url-security"
Requires-Dist: ipaddress>=1.0.23; extra == "url-security"
Provides-Extra: text-analysis
Requires-Dist: unicodedata2>=15.0.0; extra == "text-analysis"
Provides-Extra: competitor-filter
Requires-Dist: spacy>=3.5.0; extra == "competitor-filter"
Dynamic: author
Dynamic: home-page
Dynamic: license-file
Dynamic: requires-python
